[
  {
    "description": "  Validar que as credenciais permitem chamadas bem-sucedidas aos endpoints usados por este projeto.",
    "elements": [
      {
        "description": "",
        "id": "autenticacao-para-a-api-http-configurada;credenciais-validas-retornam-o-membro-autenticado",
        "keyword": "Scenario",
        "line": 8,
        "name": "credenciais validas retornam o membro autenticado",
        "steps": [
          {
            "arguments": [],
            "keyword": "Given ",
            "line": 6,
            "name": "que as credenciais estao configuradas no ambiente",
            "match": {
              "location": "step_definitions/auth.steps.js:6"
            },
            "result": {
              "status": "passed",
              "duration": 1317256
            }
          },
          {
            "arguments": [],
            "keyword": "When ",
            "line": 9,
            "name": "eu solicitar o membro autenticado da API",
            "match": {
              "location": "step_definitions/auth.steps.js:14"
            },
            "result": {
              "status": "passed",
              "duration": 251307500
            }
          },
          {
            "arguments": [],
            "keyword": "Then ",
            "line": 10,
            "name": "o status da resposta deve ser HTTP 200",
            "match": {
              "location": "step_definitions/auth.steps.js:30"
            },
            "result": {
              "status": "passed",
              "duration": 178578
            }
          },
          {
            "arguments": [],
            "keyword": "And ",
            "line": 11,
            "name": "o corpo deve conter o identificador do membro",
            "match": {
              "location": "step_definitions/auth.steps.js:34"
            },
            "result": {
              "status": "passed",
              "duration": 78239
            }
          }
        ],
        "tags": [],
        "type": "scenario"
      },
      {
        "description": "",
        "id": "autenticacao-para-a-api-http-configurada;credenciais-validas-permitem-acesso-ao-quadro-configurado",
        "keyword": "Scenario",
        "line": 13,
        "name": "credenciais validas permitem acesso ao quadro configurado",
        "steps": [
          {
            "arguments": [],
            "keyword": "Given ",
            "line": 6,
            "name": "que as credenciais estao configuradas no ambiente",
            "match": {
              "location": "step_definitions/auth.steps.js:6"
            },
            "result": {
              "status": "passed",
              "duration": 188338
            }
          },
          {
            "arguments": [],
            "keyword": "When ",
            "line": 14,
            "name": "eu solicitar o quadro configurado no ambiente",
            "match": {
              "location": "step_definitions/auth.steps.js:18"
            },
            "result": {
              "status": "passed",
              "duration": 183884451
            }
          },
          {
            "arguments": [],
            "keyword": "Then ",
            "line": 15,
            "name": "o status da resposta deve ser HTTP 200",
            "match": {
              "location": "step_definitions/auth.steps.js:30"
            },
            "result": {
              "status": "passed",
              "duration": 81169
            }
          },
          {
            "arguments": [],
            "keyword": "And ",
            "line": 16,
            "name": "o corpo deve conter o identificador do quadro",
            "match": {
              "location": "step_definitions/auth.steps.js:38"
            },
            "result": {
              "status": "passed",
              "duration": 103478
            }
          }
        ],
        "tags": [],
        "type": "scenario"
      },
      {
        "description": "",
        "id": "autenticacao-para-a-api-http-configurada;autenticacao-falha-sem-api-key",
        "keyword": "Scenario",
        "line": 18,
        "name": "autenticacao falha sem API key",
        "steps": [
          {
            "arguments": [],
            "keyword": "Given ",
            "line": 6,
            "name": "que as credenciais estao configuradas no ambiente",
            "match": {
              "location": "step_definitions/auth.steps.js:6"
            },
            "result": {
              "status": "passed",
              "duration": 212468
            }
          },
          {
            "arguments": [],
            "keyword": "When ",
            "line": 19,
            "name": "eu solicitar o membro autenticado sem API key",
            "match": {
              "location": "step_definitions/auth.steps.js:22"
            },
            "result": {
              "status": "passed",
              "duration": 143793629
            }
          },
          {
            "arguments": [],
            "keyword": "Then ",
            "line": 20,
            "name": "o status da resposta deve ser HTTP 401",
            "match": {
              "location": "step_definitions/auth.steps.js:30"
            },
            "result": {
              "status": "passed",
              "duration": 154328
            }
          },
          {
            "arguments": [],
            "keyword": "And ",
            "line": 21,
            "name": "o corpo deve conter mensagem de erro de autenticacao",
            "match": {
              "location": "step_definitions/auth.steps.js:42"
            },
            "result": {
              "status": "passed",
              "duration": 125497
            }
          }
        ],
        "tags": [],
        "type": "scenario"
      },
      {
        "description": "",
        "id": "autenticacao-para-a-api-http-configurada;autenticacao-falha-com-token-invalido",
        "keyword": "Scenario",
        "line": 23,
        "name": "autenticacao falha com token invalido",
        "steps": [
          {
            "arguments": [],
            "keyword": "Given ",
            "line": 6,
            "name": "que as credenciais estao configuradas no ambiente",
            "match": {
              "location": "step_definitions/auth.steps.js:6"
            },
            "result": {
              "status": "passed",
              "duration": 150307
            }
          },
          {
            "arguments": [],
            "keyword": "When ",
            "line": 24,
            "name": "eu solicitar o membro autenticado com token invalido",
            "match": {
              "location": "step_definitions/auth.steps.js:26"
            },
            "result": {
              "status": "passed",
              "duration": 155843898
            }
          },
          {
            "arguments": [],
            "keyword": "Then ",
            "line": 25,
            "name": "o status da resposta deve ser HTTP 401",
            "match": {
              "location": "step_definitions/auth.steps.js:30"
            },
            "result": {
              "status": "passed",
              "duration": 87399
            }
          },
          {
            "arguments": [],
            "keyword": "And ",
            "line": 26,
            "name": "o corpo deve conter mensagem de erro de autenticacao",
            "match": {
              "location": "step_definitions/auth.steps.js:42"
            },
            "result": {
              "status": "passed",
              "duration": 41459
            }
          }
        ],
        "tags": [],
        "type": "scenario"
      }
    ],
    "id": "autenticacao-para-a-api-http-configurada",
    "line": 2,
    "keyword": "Feature",
    "name": "Autenticacao para a API HTTP configurada",
    "tags": [],
    "uri": "features/01_authentication.feature"
  },
  {
    "description": "  Validar que a API consegue criar cards na lista usada por este projeto.",
    "elements": [
      {
        "description": "",
        "id": "criar-card-no-quadro-configurado;criar-um-card-com-nome-e-id-da-lista-validos",
        "keyword": "Scenario",
        "line": 9,
        "name": "criar um card com nome e id da lista validos",
        "steps": [
          {
            "arguments": [],
            "keyword": "Given ",
            "line": 6,
            "name": "que as credenciais estao configuradas no ambiente",
            "match": {
              "location": "step_definitions/auth.steps.js:6"
            },
            "result": {
              "status": "passed",
              "duration": 123669
            }
          },
          {
            "arguments": [],
            "keyword": "And ",
            "line": 7,
            "name": "que a lista de tarefas esta configurada no ambiente",
            "match": {
              "location": "step_definitions/card.steps.js:5"
            },
            "result": {
              "status": "passed",
              "duration": 73979
            }
          },
          {
            "arguments": [],
            "keyword": "When ",
            "line": 10,
            "name": "eu criar um card chamado \"Card de Teste - Automacao QA\" na lista de tarefas configurada no ambiente",
            "match": {
              "location": "step_definitions/card.steps.js:9"
            },
            "result": {
              "status": "passed",
              "duration": 369840231
            }
          },
          {
            "arguments": [],
            "keyword": "Then ",
            "line": 11,
            "name": "o status da resposta deve ser HTTP 200",
            "match": {
              "location": "step_definitions/auth.steps.js:30"
            },
            "result": {
              "status": "passed",
              "duration": 77849
            }
          },
          {
            "arguments": [],
            "keyword": "And ",
            "line": 12,
            "name": "o corpo da resposta deve conter um identificador de card",
            "match": {
              "location": "step_definitions/card.steps.js:25"
            },
            "result": {
              "status": "passed",
              "duration": 106448
            }
          }
        ],
        "tags": [],
        "type": "scenario"
      },
      {
        "description": "",
        "id": "criar-card-no-quadro-configurado;criar-um-card-sem-nome",
        "keyword": "Scenario",
        "line": 14,
        "name": "criar um card sem nome",
        "steps": [
          {
            "arguments": [],
            "keyword": "Given ",
            "line": 6,
            "name": "que as credenciais estao configuradas no ambiente",
            "match": {
              "location": "step_definitions/auth.steps.js:6"
            },
            "result": {
              "status": "passed",
              "duration": 124219
            }
          },
          {
            "arguments": [],
            "keyword": "And ",
            "line": 7,
            "name": "que a lista de tarefas esta configurada no ambiente",
            "match": {
              "location": "step_definitions/card.steps.js:5"
            },
            "result": {
              "status": "passed",
              "duration": 39059
            }
          },
          {
            "arguments": [],
            "keyword": "When ",
            "line": 15,
            "name": "eu criar um card sem nome na lista de tarefas configurada no ambiente",
            "match": {
              "location": "step_definitions/card.steps.js:13"
            },
            "result": {
              "status": "passed",
              "duration": 360189057
            }
          },
          {
            "arguments": [],
            "keyword": "Then ",
            "line": 16,
            "name": "o status da resposta deve ser HTTP 200",
            "match": {
              "location": "step_definitions/auth.steps.js:30"
            },
            "result": {
              "status": "passed",
              "duration": 70009
            }
          },
          {
            "arguments": [],
            "keyword": "And ",
            "line": 17,
            "name": "o corpo da resposta deve conter um identificador de card",
            "match": {
              "location": "step_definitions/card.steps.js:25"
            },
            "result": {
              "status": "passed",
              "duration": 114809
            }
          }
        ],
        "tags": [],
        "type": "scenario"
      },
      {
        "description": "",
        "id": "criar-card-no-quadro-configurado;criar-um-card-falha-quando-o-id-da-lista-nao-existe",
        "keyword": "Scenario",
        "line": 19,
        "name": "criar um card falha quando o id da lista nao existe",
        "steps": [
          {
            "arguments": [],
            "keyword": "Given ",
            "line": 6,
            "name": "que as credenciais estao configuradas no ambiente",
            "match": {
              "location": "step_definitions/auth.steps.js:6"
            },
            "result": {
              "status": "passed",
              "duration": 176288
            }
          },
          {
            "arguments": [],
            "keyword": "And ",
            "line": 7,
            "name": "que a lista de tarefas esta configurada no ambiente",
            "match": {
              "location": "step_definitions/card.steps.js:5"
            },
            "result": {
              "status": "passed",
              "duration": 39970
            }
          },
          {
            "arguments": [],
            "keyword": "When ",
            "line": 20,
            "name": "eu tentar criar um card chamado \"Card Teste\" no id de lista \"lista-que-nao-existe-123\"",
            "match": {
              "location": "step_definitions/card.steps.js:17"
            },
            "result": {
              "status": "passed",
              "duration": 172281246
            }
          },
          {
            "arguments": [],
            "keyword": "Then ",
            "line": 21,
            "name": "o status da resposta deve ser HTTP 400",
            "match": {
              "location": "step_definitions/auth.steps.js:30"
            },
            "result": {
              "status": "passed",
              "duration": 82018
            }
          }
        ],
        "tags": [],
        "type": "scenario"
      },
      {
        "description": "",
        "id": "criar-card-no-quadro-configurado;criar-um-card-sem-autenticacao",
        "keyword": "Scenario",
        "line": 23,
        "name": "criar um card sem autenticacao",
        "steps": [
          {
            "arguments": [],
            "keyword": "Given ",
            "line": 6,
            "name": "que as credenciais estao configuradas no ambiente",
            "match": {
              "location": "step_definitions/auth.steps.js:6"
            },
            "result": {
              "status": "passed",
              "duration": 274316
            }
          },
          {
            "arguments": [],
            "keyword": "And ",
            "line": 7,
            "name": "que a lista de tarefas esta configurada no ambiente",
            "match": {
              "location": "step_definitions/card.steps.js:5"
            },
            "result": {
              "status": "passed",
              "duration": 78218
            }
          },
          {
            "arguments": [],
            "keyword": "When ",
            "line": 24,
            "name": "eu tentar criar um card sem autenticacao",
            "match": {
              "location": "step_definitions/card.steps.js:21"
            },
            "result": {
              "status": "passed",
              "duration": 158674671
            }
          },
          {
            "arguments": [],
            "keyword": "Then ",
            "line": 25,
            "name": "o status da resposta deve ser HTTP 401",
            "match": {
              "location": "step_definitions/auth.steps.js:30"
            },
            "result": {
              "status": "passed",
              "duration": 62999
            }
          }
        ],
        "tags": [],
        "type": "scenario"
      }
    ],
    "id": "criar-card-no-quadro-configurado",
    "line": 2,
    "keyword": "Feature",
    "name": "Criar card no quadro configurado",
    "tags": [],
    "uri": "features/02_create_card.feature"
  },
  {
    "description": "  Validar que a API consegue editar diferentes atributos de um card existente.",
    "elements": [
      {
        "description": "",
        "id": "editar-card-no-quadro-configurado;editar-nome-do-card",
        "keyword": "Scenario",
        "line": 12,
        "name": "editar nome do card",
        "steps": [
          {
            "arguments": [],
            "keyword": "Given ",
            "line": 6,
            "name": "que as credenciais estao configuradas no ambiente",
            "match": {
              "location": "step_definitions/auth.steps.js:6"
            },
            "result": {
              "status": "passed",
              "duration": 153938
            }
          },
          {
            "arguments": [],
            "keyword": "And ",
            "line": 7,
            "name": "que a lista de tarefas esta configurada no ambiente",
            "match": {
              "location": "step_definitions/card.steps.js:5"
            },
            "result": {
              "status": "passed",
              "duration": 30349
            }
          },
          {
            "arguments": [],
            "keyword": "And ",
            "line": 8,
            "name": "eu criar um card chamado \"Card Base - Automacao QA\" na lista de tarefas configurada no ambiente",
            "match": {
              "location": "step_definitions/card.steps.js:9"
            },
            "result": {
              "status": "passed",
              "duration": 356086307
            }
          },
          {
            "arguments": [],
            "keyword": "And ",
            "line": 9,
            "name": "o status da resposta deve ser HTTP 200",
            "match": {
              "location": "step_definitions/auth.steps.js:30"
            },
            "result": {
              "status": "passed",
              "duration": 70068
            }
          },
          {
            "arguments": [],
            "keyword": "And ",
            "line": 10,
            "name": "o corpo da resposta deve conter um identificador de card",
            "match": {
              "location": "step_definitions/card.steps.js:25"
            },
            "result": {
              "status": "passed",
              "duration": 27009
            }
          },
          {
            "arguments": [],
            "keyword": "When ",
            "line": 13,
            "name": "eu editar o nome do card para \"Card Editado - Automacao QA\"",
            "match": {
              "location": "step_definitions/edit-card.steps.js:30"
            },
            "result": {
              "status": "passed",
              "duration": 290208173
            }
          },
          {
            "arguments": [],
            "keyword": "Then ",
            "line": 14,
            "name": "o status da resposta deve ser HTTP 200",
            "match": {
              "location": "step_definitions/auth.steps.js:30"
            },
            "result": {
              "status": "passed",
              "duration": 93039
            }
          },
          {
            "arguments": [],
            "keyword": "And ",
            "line": 15,
            "name": "o nome do card deve ser \"Card Editado - Automacao QA\"",
            "match": {
              "location": "step_definitions/edit-card.steps.js:87"
            },
            "result": {
              "status": "passed",
              "duration": 148559
            }
          }
        ],
        "tags": [],
        "type": "scenario"
      },
      {
        "description": "",
        "id": "editar-card-no-quadro-configurado;editar-descricao-do-card",
        "keyword": "Scenario",
        "line": 17,
        "name": "editar descricao do card",
        "steps": [
          {
            "arguments": [],
            "keyword": "Given ",
            "line": 6,
            "name": "que as credenciais estao configuradas no ambiente",
            "match": {
              "location": "step_definitions/auth.steps.js:6"
            },
            "result": {
              "status": "passed",
              "duration": 202588
            }
          },
          {
            "arguments": [],
            "keyword": "And ",
            "line": 7,
            "name": "que a lista de tarefas esta configurada no ambiente",
            "match": {
              "location": "step_definitions/card.steps.js:5"
            },
            "result": {
              "status": "passed",
              "duration": 67798
            }
          },
          {
            "arguments": [],
            "keyword": "And ",
            "line": 8,
            "name": "eu criar um card chamado \"Card Base - Automacao QA\" na lista de tarefas configurada no ambiente",
            "match": {
              "location": "step_definitions/card.steps.js:9"
            },
            "result": {
              "status": "passed",
              "duration": 351402474
            }
          },
          {
            "arguments": [],
            "keyword": "And ",
            "line": 9,
            "name": "o status da resposta deve ser HTTP 200",
            "match": {
              "location": "step_definitions/auth.steps.js:30"
            },
            "result": {
              "status": "passed",
              "duration": 70269
            }
          },
          {
            "arguments": [],
            "keyword": "And ",
            "line": 10,
            "name": "o corpo da resposta deve conter um identificador de card",
            "match": {
              "location": "step_definitions/card.steps.js:25"
            },
            "result": {
              "status": "passed",
              "duration": 27129
            }
          },
          {
            "arguments": [],
            "keyword": "When ",
            "line": 18,
            "name": "eu editar a descricao do card para \"Descricao adicionada pela automacao QA\"",
            "match": {
              "location": "step_definitions/edit-card.steps.js:35"
            },
            "result": {
              "status": "passed",
              "duration": 278260372
            }
          },
          {
            "arguments": [],
            "keyword": "Then ",
            "line": 19,
            "name": "o status da resposta deve ser HTTP 200",
            "match": {
              "location": "step_definitions/auth.steps.js:30"
            },
            "result": {
              "status": "passed",
              "duration": 77128
            }
          },
          {
            "arguments": [],
            "keyword": "And ",
            "line": 20,
            "name": "a descricao do card deve ser \"Descricao adicionada pela automacao QA\"",
            "match": {
              "location": "step_definitions/edit-card.steps.js:91"
            },
            "result": {
              "status": "passed",
              "duration": 106308
            }
          }
        ],
        "tags": [],
        "type": "scenario"
      },
      {
        "description": "",
        "id": "editar-card-no-quadro-configurado;adicionar-data-de-vencimento-no-card",
        "keyword": "Scenario",
        "line": 22,
        "name": "adicionar data de vencimento no card",
        "steps": [
          {
            "arguments": [],
            "keyword": "Given ",
            "line": 6,
            "name": "que as credenciais estao configuradas no ambiente",
            "match": {
              "location": "step_definitions/auth.steps.js:6"
            },
            "result": {
              "status": "passed",
              "duration": 133078
            }
          },
          {
            "arguments": [],
            "keyword": "And ",
            "line": 7,
            "name": "que a lista de tarefas esta configurada no ambiente",
            "match": {
              "location": "step_definitions/card.steps.js:5"
            },
            "result": {
              "status": "passed",
              "duration": 44799
            }
          },
          {
            "arguments": [],
            "keyword": "And ",
            "line": 8,
            "name": "eu criar um card chamado \"Card Base - Automacao QA\" na lista de tarefas configurada no ambiente",
            "match": {
              "location": "step_definitions/card.steps.js:9"
            },
            "result": {
              "status": "passed",
              "duration": 432504887
            }
          },
          {
            "arguments": [],
            "keyword": "And ",
            "line": 9,
            "name": "o status da resposta deve ser HTTP 200",
            "match": {
              "location": "step_definitions/auth.steps.js:30"
            },
            "result": {
              "status": "passed",
              "duration": 64190
            }
          },
          {
            "arguments": [],
            "keyword": "And ",
            "line": 10,
            "name": "o corpo da resposta deve conter um identificador de card",
            "match": {
              "location": "step_definitions/card.steps.js:25"
            },
            "result": {
              "status": "passed",
              "duration": 27669
            }
          },
          {
            "arguments": [],
            "keyword": "When ",
            "line": 23,
            "name": "eu definir a data de vencimento do card para \"2026-12-31T23:59:00.000Z\"",
            "match": {
              "location": "step_definitions/edit-card.steps.js:40"
            },
            "result": {
              "status": "passed",
              "duration": 296612499
            }
          },
          {
            "arguments": [],
            "keyword": "Then ",
            "line": 24,
            "name": "o status da resposta deve ser HTTP 200",
            "match": {
              "location": "step_definitions/auth.steps.js:30"
            },
            "result": {
              "status": "passed",
              "duration": 62238
            }
          },
          {
            "arguments": [],
            "keyword": "And ",
            "line": 25,
            "name": "a data de vencimento do card deve conter \"2026-12-31\"",
            "match": {
              "location": "step_definitions/edit-card.steps.js:95"
            },
            "result": {
              "status": "passed",
              "duration": 113348
            }
          }
        ],
        "tags": [],
        "type": "scenario"
      },
      {
        "description": "",
        "id": "editar-card-no-quadro-configurado;marcar-data-de-vencimento-como-concluida",
        "keyword": "Scenario",
        "line": 27,
        "name": "marcar data de vencimento como concluida",
        "steps": [
          {
            "arguments": [],
            "keyword": "Given ",
            "line": 6,
            "name": "que as credenciais estao configuradas no ambiente",
            "match": {
              "location": "step_definitions/auth.steps.js:6"
            },
            "result": {
              "status": "passed",
              "duration": 91430
            }
          },
          {
            "arguments": [],
            "keyword": "And ",
            "line": 7,
            "name": "que a lista de tarefas esta configurada no ambiente",
            "match": {
              "location": "step_definitions/card.steps.js:5"
            },
            "result": {
              "status": "passed",
              "duration": 34179
            }
          },
          {
            "arguments": [],
            "keyword": "And ",
            "line": 8,
            "name": "eu criar um card chamado \"Card Base - Automacao QA\" na lista de tarefas configurada no ambiente",
            "match": {
              "location": "step_definitions/card.steps.js:9"
            },
            "result": {
              "status": "passed",
              "duration": 369320486
            }
          },
          {
            "arguments": [],
            "keyword": "And ",
            "line": 9,
            "name": "o status da resposta deve ser HTTP 200",
            "match": {
              "location": "step_definitions/auth.steps.js:30"
            },
            "result": {
              "status": "passed",
              "duration": 66638
            }
          },
          {
            "arguments": [],
            "keyword": "And ",
            "line": 10,
            "name": "o corpo da resposta deve conter um identificador de card",
            "match": {
              "location": "step_definitions/card.steps.js:25"
            },
            "result": {
              "status": "passed",
              "duration": 33499
            }
          },
          {
            "arguments": [],
            "keyword": "Given ",
            "line": 28,
            "name": "que o card possui data de vencimento definida em \"2026-12-31T23:59:00.000Z\"",
            "match": {
              "location": "step_definitions/edit-card.steps.js:24"
            },
            "result": {
              "status": "passed",
              "duration": 288014925
            }
          },
          {
            "arguments": [],
            "keyword": "When ",
            "line": 29,
            "name": "eu marcar a data de vencimento do card como concluida",
            "match": {
              "location": "step_definitions/edit-card.steps.js:45"
            },
            "result": {
              "status": "passed",
              "duration": 339233555
            }
          },
          {
            "arguments": [],
            "keyword": "Then ",
            "line": 30,
            "name": "o status da resposta deve ser HTTP 200",
            "match": {
              "location": "step_definitions/auth.steps.js:30"
            },
            "result": {
              "status": "passed",
              "duration": 84158
            }
          },
          {
            "arguments": [],
            "keyword": "And ",
            "line": 31,
            "name": "o campo dueComplete do card deve ser true",
            "match": {
              "location": "step_definitions/edit-card.steps.js:99"
            },
            "result": {
              "status": "passed",
              "duration": 93329
            }
          }
        ],
        "tags": [],
        "type": "scenario"
      },
      {
        "description": "",
        "id": "editar-card-no-quadro-configurado;adicionar-label-no-card",
        "keyword": "Scenario",
        "line": 33,
        "name": "adicionar label no card",
        "steps": [
          {
            "arguments": [],
            "keyword": "Given ",
            "line": 6,
            "name": "que as credenciais estao configuradas no ambiente",
            "match": {
              "location": "step_definitions/auth.steps.js:6"
            },
            "result": {
              "status": "passed",
              "duration": 156437
            }
          },
          {
            "arguments": [],
            "keyword": "And ",
            "line": 7,
            "name": "que a lista de tarefas esta configurada no ambiente",
            "match": {
              "location": "step_definitions/card.steps.js:5"
            },
            "result": {
              "status": "passed",
              "duration": 48969
            }
          },
          {
            "arguments": [],
            "keyword": "And ",
            "line": 8,
            "name": "eu criar um card chamado \"Card Base - Automacao QA\" na lista de tarefas configurada no ambiente",
            "match": {
              "location": "step_definitions/card.steps.js:9"
            },
            "result": {
              "status": "passed",
              "duration": 348032568
            }
          },
          {
            "arguments": [],
            "keyword": "And ",
            "line": 9,
            "name": "o status da resposta deve ser HTTP 200",
            "match": {
              "location": "step_definitions/auth.steps.js:30"
            },
            "result": {
              "status": "passed",
              "duration": 54510
            }
          },
          {
            "arguments": [],
            "keyword": "And ",
            "line": 10,
            "name": "o corpo da resposta deve conter um identificador de card",
            "match": {
              "location": "step_definitions/card.steps.js:25"
            },
            "result": {
              "status": "passed",
              "duration": 31079
            }
          },
          {
            "arguments": [],
            "keyword": "When ",
            "line": 34,
            "name": "eu adicionar a label \"green\" no card criado",
            "match": {
              "location": "step_definitions/edit-card.steps.js:50"
            },
            "result": {
              "status": "passed",
              "duration": 527534122
            }
          },
          {
            "arguments": [],
            "keyword": "Then ",
            "line": 35,
            "name": "o status da resposta deve ser HTTP 200",
            "match": {
              "location": "step_definitions/auth.steps.js:30"
            },
            "result": {
              "status": "passed",
              "duration": 119918
            }
          },
          {
            "arguments": [],
            "keyword": "And ",
            "line": 36,
            "name": "o card deve conter a label \"green\"",
            "match": {
              "location": "step_definitions/edit-card.steps.js:103"
            },
            "result": {
              "status": "passed",
              "duration": 151528
            }
          }
        ],
        "tags": [],
        "type": "scenario"
      },
      {
        "description": "",
        "id": "editar-card-no-quadro-configurado;adicionar-membro-no-card",
        "keyword": "Scenario",
        "line": 38,
        "name": "adicionar membro no card",
        "steps": [
          {
            "arguments": [],
            "keyword": "Given ",
            "line": 6,
            "name": "que as credenciais estao configuradas no ambiente",
            "match": {
              "location": "step_definitions/auth.steps.js:6"
            },
            "result": {
              "status": "passed",
              "duration": 159947
            }
          },
          {
            "arguments": [],
            "keyword": "And ",
            "line": 7,
            "name": "que a lista de tarefas esta configurada no ambiente",
            "match": {
              "location": "step_definitions/card.steps.js:5"
            },
            "result": {
              "status": "passed",
              "duration": 39839
            }
          },
          {
            "arguments": [],
            "keyword": "And ",
            "line": 8,
            "name": "eu criar um card chamado \"Card Base - Automacao QA\" na lista de tarefas configurada no ambiente",
            "match": {
              "location": "step_definitions/card.steps.js:9"
            },
            "result": {
              "status": "passed",
              "duration": 355269875
            }
          },
          {
            "arguments": [],
            "keyword": "And ",
            "line": 9,
            "name": "o status da resposta deve ser HTTP 200",
            "match": {
              "location": "step_definitions/auth.steps.js:30"
            },
            "result": {
              "status": "passed",
              "duration": 109899
            }
          },
          {
            "arguments": [],
            "keyword": "And ",
            "line": 10,
            "name": "o corpo da resposta deve conter um identificador de card",
            "match": {
              "location": "step_definitions/card.steps.js:25"
            },
            "result": {
              "status": "passed",
              "duration": 25679
            }
          },
          {
            "arguments": [],
            "keyword": "When ",
            "line": 39,
            "name": "eu adicionar o membro autenticado no card criado",
            "match": {
              "location": "step_definitions/edit-card.steps.js:60"
            },
            "result": {
              "status": "passed",
              "duration": 481187433
            }
          },
          {
            "arguments": [],
            "keyword": "Then ",
            "line": 40,
            "name": "o status da resposta deve ser HTTP 200",
            "match": {
              "location": "step_definitions/auth.steps.js:30"
            },
            "result": {
              "status": "passed",
              "duration": 60699
            }
          },
          {
            "arguments": [],
            "keyword": "And ",
            "line": 41,
            "name": "o card deve conter o membro autenticado",
            "match": {
              "location": "step_definitions/edit-card.steps.js:107"
            },
            "result": {
              "status": "passed",
              "duration": 91379
            }
          }
        ],
        "tags": [],
        "type": "scenario"
      },
      {
        "description": "",
        "id": "editar-card-no-quadro-configurado;alterar-posicao-do-card-na-lista",
        "keyword": "Scenario",
        "line": 43,
        "name": "alterar posicao do card na lista",
        "steps": [
          {
            "arguments": [],
            "keyword": "Given ",
            "line": 6,
            "name": "que as credenciais estao configuradas no ambiente",
            "match": {
              "location": "step_definitions/auth.steps.js:6"
            },
            "result": {
              "status": "passed",
              "duration": 90968
            }
          },
          {
            "arguments": [],
            "keyword": "And ",
            "line": 7,
            "name": "que a lista de tarefas esta configurada no ambiente",
            "match": {
              "location": "step_definitions/card.steps.js:5"
            },
            "result": {
              "status": "passed",
              "duration": 31430
            }
          },
          {
            "arguments": [],
            "keyword": "And ",
            "line": 8,
            "name": "eu criar um card chamado \"Card Base - Automacao QA\" na lista de tarefas configurada no ambiente",
            "match": {
              "location": "step_definitions/card.steps.js:9"
            },
            "result": {
              "status": "passed",
              "duration": 358365415
            }
          },
          {
            "arguments": [],
            "keyword": "And ",
            "line": 9,
            "name": "o status da resposta deve ser HTTP 200",
            "match": {
              "location": "step_definitions/auth.steps.js:30"
            },
            "result": {
              "status": "passed",
              "duration": 109037
            }
          },
          {
            "arguments": [],
            "keyword": "And ",
            "line": 10,
            "name": "o corpo da resposta deve conter um identificador de card",
            "match": {
              "location": "step_definitions/card.steps.js:25"
            },
            "result": {
              "status": "passed",
              "duration": 55048
            }
          },
          {
            "arguments": [],
            "keyword": "When ",
            "line": 44,
            "name": "eu alterar a posicao do card para \"top\"",
            "match": {
              "location": "step_definitions/edit-card.steps.js:68"
            },
            "result": {
              "status": "passed",
              "duration": 271966965
            }
          },
          {
            "arguments": [],
            "keyword": "Then ",
            "line": 45,
            "name": "o status da resposta deve ser HTTP 200",
            "match": {
              "location": "step_definitions/auth.steps.js:30"
            },
            "result": {
              "status": "passed",
              "duration": 65639
            }
          },
          {
            "arguments": [],
            "keyword": "And ",
            "line": 46,
            "name": "a posicao do card deve ser numerica",
            "match": {
              "location": "step_definitions/edit-card.steps.js:111"
            },
            "result": {
              "status": "passed",
              "duration": 78588
            }
          }
        ],
        "tags": [],
        "type": "scenario"
      },
      {
        "description": "",
        "id": "editar-card-no-quadro-configurado;arquivar-card",
        "keyword": "Scenario",
        "line": 48,
        "name": "arquivar card",
        "steps": [
          {
            "arguments": [],
            "keyword": "Given ",
            "line": 6,
            "name": "que as credenciais estao configuradas no ambiente",
            "match": {
              "location": "step_definitions/auth.steps.js:6"
            },
            "result": {
              "status": "passed",
              "duration": 84439
            }
          },
          {
            "arguments": [],
            "keyword": "And ",
            "line": 7,
            "name": "que a lista de tarefas esta configurada no ambiente",
            "match": {
              "location": "step_definitions/card.steps.js:5"
            },
            "result": {
              "status": "passed",
              "duration": 19439
            }
          },
          {
            "arguments": [],
            "keyword": "And ",
            "line": 8,
            "name": "eu criar um card chamado \"Card Base - Automacao QA\" na lista de tarefas configurada no ambiente",
            "match": {
              "location": "step_definitions/card.steps.js:9"
            },
            "result": {
              "status": "passed",
              "duration": 462590618
            }
          },
          {
            "arguments": [],
            "keyword": "And ",
            "line": 9,
            "name": "o status da resposta deve ser HTTP 200",
            "match": {
              "location": "step_definitions/auth.steps.js:30"
            },
            "result": {
              "status": "passed",
              "duration": 50070
            }
          },
          {
            "arguments": [],
            "keyword": "And ",
            "line": 10,
            "name": "o corpo da resposta deve conter um identificador de card",
            "match": {
              "location": "step_definitions/card.steps.js:25"
            },
            "result": {
              "status": "passed",
              "duration": 30969
            }
          },
          {
            "arguments": [],
            "keyword": "When ",
            "line": 49,
            "name": "eu arquivar o card criado",
            "match": {
              "location": "step_definitions/edit-card.steps.js:73"
            },
            "result": {
              "status": "passed",
              "duration": 302949257
            }
          },
          {
            "arguments": [],
            "keyword": "Then ",
            "line": 50,
            "name": "o status da resposta deve ser HTTP 200",
            "match": {
              "location": "step_definitions/auth.steps.js:30"
            },
            "result": {
              "status": "passed",
              "duration": 62389
            }
          },
          {
            "arguments": [],
            "keyword": "And ",
            "line": 51,
            "name": "o campo closed do card deve ser true",
            "match": {
              "location": "step_definitions/edit-card.steps.js:115"
            },
            "result": {
              "status": "passed",
              "duration": 87868
            }
          }
        ],
        "tags": [],
        "type": "scenario"
      },
      {
        "description": "",
        "id": "editar-card-no-quadro-configurado;editar-card-com-id-inexistente",
        "keyword": "Scenario",
        "line": 53,
        "name": "editar card com id inexistente",
        "steps": [
          {
            "arguments": [],
            "keyword": "Given ",
            "line": 6,
            "name": "que as credenciais estao configuradas no ambiente",
            "match": {
              "location": "step_definitions/auth.steps.js:6"
            },
            "result": {
              "status": "passed",
              "duration": 122428
            }
          },
          {
            "arguments": [],
            "keyword": "And ",
            "line": 7,
            "name": "que a lista de tarefas esta configurada no ambiente",
            "match": {
              "location": "step_definitions/card.steps.js:5"
            },
            "result": {
              "status": "passed",
              "duration": 24330
            }
          },
          {
            "arguments": [],
            "keyword": "And ",
            "line": 8,
            "name": "eu criar um card chamado \"Card Base - Automacao QA\" na lista de tarefas configurada no ambiente",
            "match": {
              "location": "step_definitions/card.steps.js:9"
            },
            "result": {
              "status": "passed",
              "duration": 347266765
            }
          },
          {
            "arguments": [],
            "keyword": "And ",
            "line": 9,
            "name": "o status da resposta deve ser HTTP 200",
            "match": {
              "location": "step_definitions/auth.steps.js:30"
            },
            "result": {
              "status": "passed",
              "duration": 75589
            }
          },
          {
            "arguments": [],
            "keyword": "And ",
            "line": 10,
            "name": "o corpo da resposta deve conter um identificador de card",
            "match": {
              "location": "step_definitions/card.steps.js:25"
            },
            "result": {
              "status": "passed",
              "duration": 27649
            }
          },
          {
            "arguments": [],
            "keyword": "When ",
            "line": 54,
            "name": "eu tentar editar o nome do card para \"Card Invalido\" usando o id \"card-que-nao-existe-123\"",
            "match": {
              "location": "step_definitions/edit-card.steps.js:78"
            },
            "result": {
              "status": "passed",
              "duration": 165801421
            }
          },
          {
            "arguments": [],
            "keyword": "Then ",
            "line": 55,
            "name": "o status da resposta deve ser um dos HTTP 400 ou 404",
            "match": {
              "location": "step_definitions/edit-card.steps.js:119"
            },
            "result": {
              "status": "passed",
              "duration": 166048
            }
          }
        ],
        "tags": [],
        "type": "scenario"
      },
      {
        "description": "",
        "id": "editar-card-no-quadro-configurado;editar-card-sem-autenticacao",
        "keyword": "Scenario",
        "line": 57,
        "name": "editar card sem autenticacao",
        "steps": [
          {
            "arguments": [],
            "keyword": "Given ",
            "line": 6,
            "name": "que as credenciais estao configuradas no ambiente",
            "match": {
              "location": "step_definitions/auth.steps.js:6"
            },
            "result": {
              "status": "passed",
              "duration": 104099
            }
          },
          {
            "arguments": [],
            "keyword": "And ",
            "line": 7,
            "name": "que a lista de tarefas esta configurada no ambiente",
            "match": {
              "location": "step_definitions/card.steps.js:5"
            },
            "result": {
              "status": "passed",
              "duration": 22968
            }
          },
          {
            "arguments": [],
            "keyword": "And ",
            "line": 8,
            "name": "eu criar um card chamado \"Card Base - Automacao QA\" na lista de tarefas configurada no ambiente",
            "match": {
              "location": "step_definitions/card.steps.js:9"
            },
            "result": {
              "status": "passed",
              "duration": 322900128
            }
          },
          {
            "arguments": [],
            "keyword": "And ",
            "line": 9,
            "name": "o status da resposta deve ser HTTP 200",
            "match": {
              "location": "step_definitions/auth.steps.js:30"
            },
            "result": {
              "status": "passed",
              "duration": 113757
            }
          },
          {
            "arguments": [],
            "keyword": "And ",
            "line": 10,
            "name": "o corpo da resposta deve conter um identificador de card",
            "match": {
              "location": "step_definitions/card.steps.js:25"
            },
            "result": {
              "status": "passed",
              "duration": 49238
            }
          },
          {
            "arguments": [],
            "keyword": "When ",
            "line": 58,
            "name": "eu tentar editar o card sem autenticacao",
            "match": {
              "location": "step_definitions/edit-card.steps.js:82"
            },
            "result": {
              "status": "passed",
              "duration": 156342233
            }
          },
          {
            "arguments": [],
            "keyword": "Then ",
            "line": 59,
            "name": "o status da resposta deve ser um dos HTTP 401 ou 403",
            "match": {
              "location": "step_definitions/edit-card.steps.js:119"
            },
            "result": {
              "status": "passed",
              "duration": 95379
            }
          }
        ],
        "tags": [],
        "type": "scenario"
      }
    ],
    "id": "editar-card-no-quadro-configurado",
    "line": 2,
    "keyword": "Feature",
    "name": "Editar card no quadro configurado",
    "tags": [],
    "uri": "features/03_edit_card.feature"
  },
  {
    "description": "  Validar que a API consegue excluir cards e tratar erros esperados.",
    "elements": [
      {
        "description": "",
        "id": "excluir-card-no-quadro-configurado;excluir-card-criado-e-confirmar-exclusao-via-get",
        "keyword": "Scenario",
        "line": 12,
        "name": "excluir card criado e confirmar exclusao via GET",
        "steps": [
          {
            "arguments": [],
            "keyword": "Given ",
            "line": 6,
            "name": "que as credenciais estao configuradas no ambiente",
            "match": {
              "location": "step_definitions/auth.steps.js:6"
            },
            "result": {
              "status": "passed",
              "duration": 110859
            }
          },
          {
            "arguments": [],
            "keyword": "And ",
            "line": 7,
            "name": "que a lista de tarefas esta configurada no ambiente",
            "match": {
              "location": "step_definitions/card.steps.js:5"
            },
            "result": {
              "status": "passed",
              "duration": 38569
            }
          },
          {
            "arguments": [],
            "keyword": "And ",
            "line": 8,
            "name": "eu criar um card chamado \"Card Base - Delete QA\" na lista de tarefas configurada no ambiente",
            "match": {
              "location": "step_definitions/card.steps.js:9"
            },
            "result": {
              "status": "passed",
              "duration": 345432963
            }
          },
          {
            "arguments": [],
            "keyword": "And ",
            "line": 9,
            "name": "o status da resposta deve ser HTTP 200",
            "match": {
              "location": "step_definitions/auth.steps.js:30"
            },
            "result": {
              "status": "passed",
              "duration": 93869
            }
          },
          {
            "arguments": [],
            "keyword": "And ",
            "line": 10,
            "name": "o corpo da resposta deve conter um identificador de card",
            "match": {
              "location": "step_definitions/card.steps.js:25"
            },
            "result": {
              "status": "passed",
              "duration": 42669
            }
          },
          {
            "arguments": [],
            "keyword": "When ",
            "line": 13,
            "name": "eu excluir o card criado",
            "match": {
              "location": "step_definitions/delete-card.steps.js:15"
            },
            "result": {
              "status": "passed",
              "duration": 319027286
            }
          },
          {
            "arguments": [],
            "keyword": "Then ",
            "line": 14,
            "name": "o status da resposta deve ser HTTP 200",
            "match": {
              "location": "step_definitions/auth.steps.js:30"
            },
            "result": {
              "status": "passed",
              "duration": 113509
            }
          },
          {
            "arguments": [],
            "keyword": "And ",
            "line": 15,
            "name": "o corpo deve confirmar exclusao do card",
            "match": {
              "location": "step_definitions/delete-card.steps.js:39"
            },
            "result": {
              "status": "passed",
              "duration": 179137
            }
          },
          {
            "arguments": [],
            "keyword": "When ",
            "line": 16,
            "name": "eu buscar o card criado via GET",
            "match": {
              "location": "step_definitions/delete-card.steps.js:25"
            },
            "result": {
              "status": "passed",
              "duration": 170681182
            }
          },
          {
            "arguments": [],
            "keyword": "Then ",
            "line": 17,
            "name": "o status da resposta deve ser um dos HTTP 400 ou 404",
            "match": {
              "location": "step_definitions/edit-card.steps.js:119"
            },
            "result": {
              "status": "passed",
              "duration": 76009
            }
          }
        ],
        "tags": [],
        "type": "scenario"
      },
      {
        "description": "",
        "id": "excluir-card-no-quadro-configurado;tentar-excluir-card-ja-excluido",
        "keyword": "Scenario",
        "line": 19,
        "name": "tentar excluir card ja excluido",
        "steps": [
          {
            "arguments": [],
            "keyword": "Given ",
            "line": 6,
            "name": "que as credenciais estao configuradas no ambiente",
            "match": {
              "location": "step_definitions/auth.steps.js:6"
            },
            "result": {
              "status": "passed",
              "duration": 140669
            }
          },
          {
            "arguments": [],
            "keyword": "And ",
            "line": 7,
            "name": "que a lista de tarefas esta configurada no ambiente",
            "match": {
              "location": "step_definitions/card.steps.js:5"
            },
            "result": {
              "status": "passed",
              "duration": 28570
            }
          },
          {
            "arguments": [],
            "keyword": "And ",
            "line": 8,
            "name": "eu criar um card chamado \"Card Base - Delete QA\" na lista de tarefas configurada no ambiente",
            "match": {
              "location": "step_definitions/card.steps.js:9"
            },
            "result": {
              "status": "passed",
              "duration": 673003646
            }
          },
          {
            "arguments": [],
            "keyword": "And ",
            "line": 9,
            "name": "o status da resposta deve ser HTTP 200",
            "match": {
              "location": "step_definitions/auth.steps.js:30"
            },
            "result": {
              "status": "passed",
              "duration": 85709
            }
          },
          {
            "arguments": [],
            "keyword": "And ",
            "line": 10,
            "name": "o corpo da resposta deve conter um identificador de card",
            "match": {
              "location": "step_definitions/card.steps.js:25"
            },
            "result": {
              "status": "passed",
              "duration": 31570
            }
          },
          {
            "arguments": [],
            "keyword": "When ",
            "line": 20,
            "name": "eu excluir o card criado",
            "match": {
              "location": "step_definitions/delete-card.steps.js:15"
            },
            "result": {
              "status": "passed",
              "duration": 325697040
            }
          },
          {
            "arguments": [],
            "keyword": "Then ",
            "line": 21,
            "name": "o status da resposta deve ser HTTP 200",
            "match": {
              "location": "step_definitions/auth.steps.js:30"
            },
            "result": {
              "status": "passed",
              "duration": 65408
            }
          },
          {
            "arguments": [],
            "keyword": "When ",
            "line": 22,
            "name": "eu excluir o card criado novamente",
            "match": {
              "location": "step_definitions/delete-card.steps.js:20"
            },
            "result": {
              "status": "passed",
              "duration": 168694921
            }
          },
          {
            "arguments": [],
            "keyword": "Then ",
            "line": 23,
            "name": "o status da resposta deve ser um dos HTTP 400 ou 404",
            "match": {
              "location": "step_definitions/edit-card.steps.js:119"
            },
            "result": {
              "status": "passed",
              "duration": 111678
            }
          }
        ],
        "tags": [],
        "type": "scenario"
      },
      {
        "description": "",
        "id": "excluir-card-no-quadro-configurado;tentar-excluir-card-com-id-invalido",
        "keyword": "Scenario",
        "line": 25,
        "name": "tentar excluir card com id invalido",
        "steps": [
          {
            "arguments": [],
            "keyword": "Given ",
            "line": 6,
            "name": "que as credenciais estao configuradas no ambiente",
            "match": {
              "location": "step_definitions/auth.steps.js:6"
            },
            "result": {
              "status": "passed",
              "duration": 144048
            }
          },
          {
            "arguments": [],
            "keyword": "And ",
            "line": 7,
            "name": "que a lista de tarefas esta configurada no ambiente",
            "match": {
              "location": "step_definitions/card.steps.js:5"
            },
            "result": {
              "status": "passed",
              "duration": 35529
            }
          },
          {
            "arguments": [],
            "keyword": "And ",
            "line": 8,
            "name": "eu criar um card chamado \"Card Base - Delete QA\" na lista de tarefas configurada no ambiente",
            "match": {
              "location": "step_definitions/card.steps.js:9"
            },
            "result": {
              "status": "passed",
              "duration": 369269855
            }
          },
          {
            "arguments": [],
            "keyword": "And ",
            "line": 9,
            "name": "o status da resposta deve ser HTTP 200",
            "match": {
              "location": "step_definitions/auth.steps.js:30"
            },
            "result": {
              "status": "passed",
              "duration": 64269
            }
          },
          {
            "arguments": [],
            "keyword": "And ",
            "line": 10,
            "name": "o corpo da resposta deve conter um identificador de card",
            "match": {
              "location": "step_definitions/card.steps.js:25"
            },
            "result": {
              "status": "passed",
              "duration": 42878
            }
          },
          {
            "arguments": [],
            "keyword": "When ",
            "line": 26,
            "name": "eu tentar excluir o card com o id \"id-invalido-123\"",
            "match": {
              "location": "step_definitions/delete-card.steps.js:30"
            },
            "result": {
              "status": "passed",
              "duration": 168575473
            }
          },
          {
            "arguments": [],
            "keyword": "Then ",
            "line": 27,
            "name": "o status da resposta deve ser um dos HTTP 400 ou 404",
            "match": {
              "location": "step_definitions/edit-card.steps.js:119"
            },
            "result": {
              "status": "passed",
              "duration": 69088
            }
          }
        ],
        "tags": [],
        "type": "scenario"
      },
      {
        "description": "",
        "id": "excluir-card-no-quadro-configurado;excluir-card-sem-autenticacao",
        "keyword": "Scenario",
        "line": 29,
        "name": "excluir card sem autenticacao",
        "steps": [
          {
            "arguments": [],
            "keyword": "Given ",
            "line": 6,
            "name": "que as credenciais estao configuradas no ambiente",
            "match": {
              "location": "step_definitions/auth.steps.js:6"
            },
            "result": {
              "status": "passed",
              "duration": 112439
            }
          },
          {
            "arguments": [],
            "keyword": "And ",
            "line": 7,
            "name": "que a lista de tarefas esta configurada no ambiente",
            "match": {
              "location": "step_definitions/card.steps.js:5"
            },
            "result": {
              "status": "passed",
              "duration": 33890
            }
          },
          {
            "arguments": [],
            "keyword": "And ",
            "line": 8,
            "name": "eu criar um card chamado \"Card Base - Delete QA\" na lista de tarefas configurada no ambiente",
            "match": {
              "location": "step_definitions/card.steps.js:9"
            },
            "result": {
              "status": "passed",
              "duration": 717473722
            }
          },
          {
            "arguments": [],
            "keyword": "And ",
            "line": 9,
            "name": "o status da resposta deve ser HTTP 200",
            "match": {
              "location": "step_definitions/auth.steps.js:30"
            },
            "result": {
              "status": "passed",
              "duration": 54560
            }
          },
          {
            "arguments": [],
            "keyword": "And ",
            "line": 10,
            "name": "o corpo da resposta deve conter um identificador de card",
            "match": {
              "location": "step_definitions/card.steps.js:25"
            },
            "result": {
              "status": "passed",
              "duration": 24570
            }
          },
          {
            "arguments": [],
            "keyword": "When ",
            "line": 30,
            "name": "eu tentar excluir o card criado sem autenticacao",
            "match": {
              "location": "step_definitions/delete-card.steps.js:34"
            },
            "result": {
              "status": "passed",
              "duration": 153946218
            }
          },
          {
            "arguments": [],
            "keyword": "Then ",
            "line": 31,
            "name": "o status da resposta deve ser um dos HTTP 401 ou 403",
            "match": {
              "location": "step_definitions/edit-card.steps.js:119"
            },
            "result": {
              "status": "passed",
              "duration": 145927
            }
          }
        ],
        "tags": [],
        "type": "scenario"
      }
    ],
    "id": "excluir-card-no-quadro-configurado",
    "line": 2,
    "keyword": "Feature",
    "name": "Excluir card no quadro configurado",
    "tags": [],
    "uri": "features/04_delete_card.feature"
  }
]